pyramid_services/__init__.py
pyramid_services-2.2.dist-info/LICENSE.txt
pyramid_services-2.2.dist-info/METADATA
pyramid_services-2.2.dist-info/WHEEL
pyramid_services-2.2.dist-info/top_level.txt
pyramid_services-2.2.dist-info/RECORD
