Metadata-Version: 2.1
Name: pyramid-services
Version: 2.2
Summary: A service layer abstraction for the Pyramid Web Framework.
Home-page: https://github.com/mmerickel/pyramid_services
Author: Michael Merickel
Author-email: pylons-discuss@googlegroups.com
License: MIT
Keywords: pyramid,services,service layer,ioc container
Platform: UNKNOWN
Classifier: Development Status :: 5 - Production/Stable
Classifier: Framework :: Pyramid
Classifier: Intended Audience :: Developers
Classifier: License :: OSI Approved :: MIT License
Classifier: Programming Language :: Python
Classifier: Programming Language :: Python :: 3
Classifier: Programming Language :: Python :: 3.4
Classifier: Programming Language :: Python :: 3.5
Classifier: Programming Language :: Python :: 3.6
Classifier: Programming Language :: Python :: Implementation :: CPython
Classifier: Programming Language :: Python :: Implementation :: PyPy
Requires-Python: >=3.3
Requires-Dist: pyramid
Requires-Dist: wired (>=0.2)
Requires-Dist: zope.interface
Provides-Extra: testing
Requires-Dist: pyramid ; extra == 'testing'
Requires-Dist: wired (>=0.2) ; extra == 'testing'
Requires-Dist: zope.interface ; extra == 'testing'
Requires-Dist: pytest ; extra == 'testing'
Requires-Dist: pytest-cov ; extra == 'testing'
Requires-Dist: webtest ; extra == 'testing'
